hdf5.dll
hdf5_hl.dll
libcurl.dll
netcdf.dll
py3dti.cp311-win32.pyd
python311.dll
zlib1.dll
py3dti-0.3.0.dist-info/METADATA
py3dti-0.3.0.dist-info/WHEEL
py3dti-0.3.0.dist-info/entry_points.txt
py3dti-0.3.0.dist-info/licenses/LICENSE
py3dti-0.3.0.dist-info/RECORD
