Metadata-Version: 2.1
Name: py3dti
Version: 0.3.0
Summary: Python bindings for the 3dti Audio Spatialiser.
Author-Email: Johan Pauwels <johan.pauwels@gmail.com>
Classifier: Development Status :: 4 - Beta
Classifier: License :: OSI Approved :: GNU General Public License v3 (GPLv3)
Classifier: Programming Language :: Python :: 3 :: Only
Classifier: Programming Language :: Python :: 3.8
Classifier: Programming Language :: Python :: 3.9
Classifier: Programming Language :: Python :: 3.10
Classifier: Programming Language :: Python :: 3.11
Classifier: Programming Language :: Python :: 3.12
Requires-Python: >=3.8
Provides-Extra: test
Requires-Dist: pytest; extra == "test"
License-File: LICENSE
